{
  "decision": {
    "case_ref": "SYN-MCHK-2024-001",
    "case_refs": [
      "SYN-MCHK-2024-001"
    ],
    "coverage": {
      "missing_fields": [],
      "warnings": []
    },
    "dates": {
      "conduct": null,
      "inquiry": "2024-03-15",
      "judgment": "2024-03-15",
      "order_effective": null,
      "publication": null
    },
    "decision_date": "2024-03-15",
    "defendant_name_as_published": "Dr Jane Example",
    "defendant_registration_no": "M99999",
    "document_id": "1c31ed90-b5db-5320-af82-96c097acaaf7",
    "document_sha256": "8de4cc2091224b859147bb2186759a818f2e01cef222857ca621594318ec70e3",
    "extraction_sha256": "44de0df30c1c07754537ffc63a265df6edf5750353e1b7bcb211d793f5f1ef63",
    "extractor": {
      "model_provider": "mock",
      "model_version": "mock-2.0.0",
      "pipeline_version": "m2a.0.0",
      "prompt_version": "mock-prompt-2.0.0"
    },
    "fixture_kind": "synthetic",
    "generated_at": "2026-07-11T11:37:53+00:00",
    "id": "95db05b2-72a0-5849-ae8a-5a001a318196",
    "licence_notice": "Internal research use of fixture materials only. Not legal advice. Synthetic demo pointer is not the audit record.",
    "pages": [
      {
        "page_no": 1,
        "printed_page_label": null,
        "quality": "good",
        "source_page_no": 1,
        "span_id": "be1f758fa20ddc2e58d34954885d8760",
        "text": "The Medical Council of Hong Kong (Synthetic)\nDISCIPLINARY INQUIRY\nMedical Registration Ordinance, Cap. 161\nCase Reference: SYN-MCHK-2024-001\nDefendant: Dr Jane Example (Reg. No.: M99999)\nDate of hearing: 15 March 2024\nCharge: That she, being a registered medical practitioner, failed to keep adequate clinical records in respect of Patient A, and in relation to the facts alleged was guilty of misconduct in a professional respect.\nThe charge is brought under the Medical Registration Ordinance and the Code of Professional Conduct."
      },
      {
        "page_no": 2,
        "printed_page_label": null,
        "quality": "good",
        "source_page_no": 2,
        "span_id": "f617d30d878d12f7e0bcb4524397ee1e",
        "text": "Findings\nFinding: The Council is satisfied that the charge is proved and that the Defendant is guilty of misconduct in a professional respect.\nThe Council applies the legal standard that conduct which falls short of the standard expected of a registered medical practitioner may constitute misconduct.\nThe Defendant has a clear disciplinary record and made an admission of the facts at the outset.\nThe Council has considered Dr Chan v. The Medical Council of Hong Kong as a cited authority on professional endorsement principles, by analogy only in this synthetic fixture."
      },
      {
        "page_no": 3,
        "printed_page_label": null,
        "quality": "good",
        "source_page_no": 3,
        "span_id": "7eec97f0d2519c60642d28dfa03de879",
        "text": "Order\nOrder: The Defendant be served with a warning letter. The removal order is not required. No appeal is recorded in this synthetic fixture.\nCosts: No order as to costs."
      }
    ],
    "pipeline_version": "m2a.0.0",
    "profession": "doctor",
    "propositions": [
      {
        "claim_text": "That she, being a registered medical practitioner, failed to keep adequate clinical records in respect of Patient A, and in relation to the facts alleged was guilty of misconduct in a professional respect.",
        "client_ref": "charge-1",
        "confidence": 0.85,
        "derivation": "normalized",
        "epistemic_class": "fact",
        "evidence": [
          {
            "char_end": 406,
            "char_start": 226,
            "page_no": 1,
            "quote": "That she, being a registered medical practitioner, failed to keep adequate clinical records in respect of Patient A, and in relation to the facts alleged was guilty of misconduct i",
            "span_id": "be1f758fa20ddc2e58d34954885d8760"
          }
        ],
        "id": "672fa7b3-519c-5055-82e0-6334a15af9c3",
        "prop_type": "charge",
        "published": true,
        "review_status": "accepted",
        "structured": {
          "charge_text": "That she, being a registered medical practitioner, failed to keep adequate clinical records in respect of Patient A, and in relation to the facts alleged was guilty of misconduct in a professional respect."
        }
      },
      {
        "claim_text": "Medical Registration Ordinance, Cap",
        "client_ref": "rule-1",
        "confidence": 0.8,
        "derivation": "verbatim",
        "epistemic_class": "fact",
        "evidence": [
          {
            "char_end": 101,
            "char_start": 66,
            "page_no": 1,
            "quote": "Medical Registration Ordinance, Cap",
            "span_id": "be1f758fa20ddc2e58d34954885d8760"
          }
        ],
        "id": "634ee533-8cf8-5a9c-b130-abed45ceb850",
        "prop_type": "rule",
        "published": true,
        "review_status": "accepted",
        "structured": {
          "instrument": "Medical Registration Ordinance, Cap"
        }
      },
      {
        "claim_text": "The Council is satisfied that the charge is proved and that the Defendant is guilty of misconduct in a professional respect.",
        "client_ref": "finding-1",
        "confidence": 0.82,
        "derivation": "normalized",
        "epistemic_class": "fact",
        "evidence": [
          {
            "char_end": 142,
            "char_start": 18,
            "page_no": 2,
            "quote": "The Council is satisfied that the charge is proved and that the Defendant is guilty of misconduct in a professional respect.",
            "span_id": "f617d30d878d12f7e0bcb4524397ee1e"
          }
        ],
        "id": "684c6954-fa3f-5ce7-97fd-c9261cb3b6ed",
        "prop_type": "finding",
        "published": true,
        "review_status": "accepted",
        "structured": {
          "outcome": "proved"
        }
      },
      {
        "claim_text": "The Defendant be served with a warning letter. The removal order is not required. No appeal is recorded in this synthetic fixture.",
        "client_ref": "sanction-1",
        "confidence": 0.84,
        "derivation": "normalized",
        "epistemic_class": "fact",
        "evidence": [
          {
            "char_end": 143,
            "char_start": 13,
            "page_no": 3,
            "quote": "The Defendant be served with a warning letter. The removal order is not required. No appeal is recorded in this synthetic fixture.",
            "span_id": "7eec97f0d2519c60642d28dfa03de879"
          }
        ],
        "id": "090d7328-57ce-5cea-8bdd-c0eae0eb02bb",
        "prop_type": "sanction",
        "published": true,
        "review_status": "accepted",
        "structured": {
          "order_text": "The Defendant be served with a warning letter. The removal order is not required. No appeal is recorded in this synthetic fixture."
        }
      },
      {
        "claim_text": "clear disciplinary record",
        "client_ref": "mitigating-factor-1",
        "confidence": 0.75,
        "derivation": "verbatim",
        "epistemic_class": "fact",
        "evidence": [
          {
            "char_end": 347,
            "char_start": 322,
            "page_no": 2,
            "quote": "clear disciplinary record",
            "span_id": "f617d30d878d12f7e0bcb4524397ee1e"
          }
        ],
        "id": "0e7e2ed5-4be2-5fb3-b890-f5a1814308a8",
        "prop_type": "mitigating_factor",
        "published": true,
        "review_status": "accepted",
        "structured": {
          "polarity": "mitigating"
        }
      },
      {
        "claim_text": "Dr Chan v. The Medical Council of Hong Kong as a cited authority on pr",
        "client_ref": "authority-1",
        "confidence": 0.7,
        "derivation": "verbatim",
        "epistemic_class": "fact",
        "evidence": [
          {
            "char_end": 495,
            "char_start": 425,
            "page_no": 2,
            "quote": "Dr Chan v. The Medical Council of Hong Kong as a cited authority on pr",
            "span_id": "f617d30d878d12f7e0bcb4524397ee1e"
          }
        ],
        "id": "8672b345-06bf-5f4b-a47b-aed0d1a99e9c",
        "prop_type": "authority",
        "published": true,
        "review_status": "accepted",
        "structured": {
          "citation": "Dr Chan v. The Medical Council of Hong Kong as a cited authority on pr"
        }
      },
      {
        "claim_text": "No appeal",
        "client_ref": "appeal-status-1",
        "confidence": 0.7,
        "derivation": "normalized",
        "epistemic_class": "fact",
        "evidence": [
          {
            "char_end": 104,
            "char_start": 95,
            "page_no": 3,
            "quote": "No appeal",
            "span_id": "7eec97f0d2519c60642d28dfa03de879"
          }
        ],
        "id": "d7bc8ede-6be8-5484-bd93-d36c101c94fe",
        "prop_type": "appeal_status",
        "published": true,
        "review_status": "accepted",
        "structured": null
      },
      {
        "claim_text": "conduct which falls short of the standard expected of a registered medical practitioner may constitute misconduct",
        "client_ref": "legal-test-1",
        "confidence": 0.65,
        "derivation": "inferred",
        "epistemic_class": "interpretation",
        "evidence": [
          {
            "char_end": 300,
            "char_start": 187,
            "page_no": 2,
            "quote": "conduct which falls short of the standard expected of a registered medical practitioner may constitute misconduct",
            "span_id": "f617d30d878d12f7e0bcb4524397ee1e"
          }
        ],
        "id": "858efba8-8bdd-5613-b04b-eb128365ef10",
        "prop_type": "legal_test",
        "published": true,
        "review_status": "accepted",
        "structured": {
          "test_label": "standard_expected"
        }
      }
    ],
    "regulator_code": "MCHK",
    "relations": [
      {
        "from_ref": "finding-1",
        "relation_type": "finding_resolves_charge",
        "to_ref": "charge-1"
      },
      {
        "from_ref": "sanction-1",
        "relation_type": "sanction_applies_to_charge",
        "to_ref": "charge-1"
      },
      {
        "from_ref": "rule-1",
        "relation_type": "rule_governs_charge",
        "to_ref": "charge-1"
      },
      {
        "from_ref": "authority-1",
        "relation_type": "authority_supports_legal_test",
        "to_ref": "legal-test-1"
      },
      {
        "from_ref": "mitigating-factor-1",
        "relation_type": "factor_affects_sanction",
        "to_ref": "sanction-1"
      }
    ],
    "run_key": "17fe5c64f969fa80d0b5aeead3b8bf26b69892ac75c184b2edbc65711dafd00c",
    "segmentation_warnings": [],
    "source_id": "mchk_judgments",
    "source_url": null,
    "text_quality": "good",
    "title": "Synthetic MCHK decision SYN-MCHK-2024-001"
  },
  "decision_id": "95db05b2-72a0-5849-ae8a-5a001a318196",
  "immutable_decision_path": "meta/runs/17fe5c64f969fa80d0b5aeead3b8bf26b69892ac75c184b2edbc65711dafd00c/decision.json",
  "immutable_extraction_path": "meta/runs/17fe5c64f969fa80d0b5aeead3b8bf26b69892ac75c184b2edbc65711dafd00c/extraction.json",
  "pointer_kind": "synthetic_demo",
  "run_key": "17fe5c64f969fa80d0b5aeead3b8bf26b69892ac75c184b2edbc65711dafd00c"
}
